ggpyscraper/__init__.py
ggpyscraper/liquipedia_objects/__init__.py
ggpyscraper/liquipedia_objects/liquipedia_page.py
ggpyscraper/liquipedia_objects/player.py
ggpyscraper/liquipedia_objects/team.py
ggpyscraper/liquipedia_objects/tournament.py
ggpyscraper/parse_liquipedia/__init__.py
ggpyscraper/parse_liquipedia/parse_general_pages.py
ggpyscraper/parse_liquipedia/parse_liquipedia_html.py
ggpyscraper/parse_liquipedia/parse_liquipedia_wc.py
ggpyscraper/parse_liquipedia/parse_multiple_liquipedia_pages.py
ggpyscraper-0.0.3.3.dist-info/METADATA
ggpyscraper-0.0.3.3.dist-info/WHEEL
ggpyscraper-0.0.3.3.dist-info/licenses/LICENSE
ggpyscraper-0.0.3.3.dist-info/RECORD
